{
  "text": "Hello, from the other side, I must have called a thousand times. hello dnd me mewo squirtle gross pikachu charmander is store my name",
  "images": [
    "sample_images\\page_1.png",
    "sample_images\\page_1_img_53.png",
    "sample_images\\page_1_img_59.png",
    "sample_images\\page_1_img_72.png"
  ],
  "tables": [
    {
      "data": [
        {
          "Hello, from the other side, I must have called a thousand times.\r\r\rhellomewogrossstore\rdndsquirtlepikachumy\rmecharmanderisname": "hello",
          "Unnamed: 0": "mewo",
          "Unnamed: 1": "gross",
          "Unnamed: 2": "store"
        },
        {
          "Hello, from the other side, I must have called a thousand times.\r\r\rhellomewogrossstore\rdndsquirtlepikachumy\rmecharmanderisname": "dnd",
          "Unnamed: 0": "squirtle",
          "Unnamed: 1": "pikachu",
          "Unnamed: 2": "my"
        },
        {
          "Hello, from the other side, I must have called a thousand times.\r\r\rhellomewogrossstore\rdndsquirtlepikachumy\rmecharmanderisname": "me",
          "Unnamed: 0": "charmander",
          "Unnamed: 1": "is",
          "Unnamed: 2": "name"
        }
      ],
      "shape": [
        3,
        4
      ],
      "confidence": 0.8
    },
    {
      "data": [
        {
          "Hello, from the other side, I must have called a thousand times.\r\r\rhellomewogrossstore\rdndsquirtlepikachumy\rmecharmanderisname": "hello",
          "Unnamed: 0": "mewo",
          "Unnamed: 1": "gross",
          "Unnamed: 2": "store"
        },
        {
          "Hello, from the other side, I must have called a thousand times.\r\r\rhellomewogrossstore\rdndsquirtlepikachumy\rmecharmanderisname": "dnd",
          "Unnamed: 0": "squirtle",
          "Unnamed: 1": "pikachu",
          "Unnamed: 2": "my"
        },
        {
          "Hello, from the other side, I must have called a thousand times.\r\r\rhellomewogrossstore\rdndsquirtlepikachumy\rmecharmanderisname": "me",
          "Unnamed: 0": "charmander",
          "Unnamed: 1": "is",
          "Unnamed: 2": "name"
        }
      ],
      "shape": [
        3,
        4
      ],
      "confidence": 0.8
    }
  ],
  "forms": [],
  "handwritten_content": [],
  "metadata": {
    "file_name": "sample.pdf",
    "file_size": 887002,
    "page_count": 1,
    "extraction_method": "pdfminer + tabula",
    "text_length": 133,
    "tables_found": 2,
    "forms_found": 0,
    "images_found": 4,
    "handwritten_items_found": 0
  }
}